nonebot_plugin_asoulcnki/__init__.py
nonebot_plugin_asoulcnki/data_source.py
nonebot_plugin_asoulcnki/diff.py
nonebot_plugin_asoulcnki/templates/article.html
nonebot_plugin_asoulcnki-0.2.1.dist-info/LICENSE
nonebot_plugin_asoulcnki-0.2.1.dist-info/WHEEL
nonebot_plugin_asoulcnki-0.2.1.dist-info/METADATA
nonebot_plugin_asoulcnki-0.2.1.dist-info/RECORD
