Metadata-Version: 2.1
Name: nonebot-plugin-asoulcnki
Version: 0.2.1
Summary: ASoulCnki plugin for Nonebot2
Home-page: https://github.com/noneplugin/nonebot-plugin-asoulcnki
License: MIT
Author: meetwq
Author-email: meetwq@gmail.com
Requires-Python: >=3.7.3,<4.0.0
Classifier: License :: OSI Approved :: MIT License
Classifier: Programming Language :: Python :: 3
Classifier: Programming Language :: Python :: 3.10
Classifier: Programming Language :: Python :: 3.8
Classifier: Programming Language :: Python :: 3.9
Requires-Dist: Jinja2 (>=3.0.0,<4.0.0)
Requires-Dist: httpx (>=0.19.0)
Requires-Dist: nonebot-adapter-onebot (>=2.0.0-beta.1,<3.0.0)
Requires-Dist: nonebot-plugin-htmlrender (>=0.0.4)
Requires-Dist: nonebot2 (>=2.0.0-beta.4,<3.0.0)
Project-URL: Repository, https://github.com/noneplugin/nonebot-plugin-asoulcnki
